cm_decor.py
ct.py
cm_decor-0.1.3.dist-info/LICENSE
cm_decor-0.1.3.dist-info/METADATA
cm_decor-0.1.3.dist-info/WHEEL
cm_decor-0.1.3.dist-info/top_level.txt
cm_decor-0.1.3.dist-info/RECORD
