Metadata-Version: 2.1
Name: cm-decor
Version: 0.1.3
Summary: cm_decor
Author: Vitalii Abetkin
Author-email: abvit89s@gmail.ru
License: MIT
License-File: LICENSE
